{
 "metadata": {
  "duration": 1.354,
  "source": "faster-whisper+cmudict"
 },
 "mouthCues": [
  {
   "start": 0.0,
   "end": 0.054,
   "value": "mbp"
  },
  {
   "start": 0.054,
   "end": 0.14,
   "value": "e"
  },
  {
   "start": 0.14,
   "end": 0.32,
   "value": "a"
  },
  {
   "start": 0.32,
   "end": 0.37,
   "value": "ts"
  },
  {
   "start": 0.37,
   "end": 0.45,
   "value": "e"
  },
  {
   "start": 0.45,
   "end": 0.5,
   "value": "fv"
  },
  {
   "start": 0.5,
   "end": 0.56,
   "value": "a"
  },
  {
   "start": 0.56,
   "end": 0.632,
   "value": "ts"
  },
  {
   "start": 0.632,
   "end": 0.748,
   "value": "e"
  },
  {
   "start": 0.748,
   "end": 0.82,
   "value": "ln"
  },
  {
   "start": 0.82,
   "end": 0.868,
   "value": "mbp"
  },
  {
   "start": 0.868,
   "end": 0.916,
   "value": "ln"
  },
  {
   "start": 0.916,
   "end": 0.992,
   "value": "e"
  },
  {
   "start": 0.992,
   "end": 1.04,
   "value": "ts"
  },
  {
   "start": 1.04,
   "end": 1.354,
   "value": "rest"
  }
 ]
}