{
 "metadata": {
  "duration": 2.391,
  "source": "faster-whisper+cmudict"
 },
 "mouthCues": [
  {
   "start": 0.0,
   "end": 0.26,
   "value": "uq"
  },
  {
   "start": 0.26,
   "end": 0.72,
   "value": "rest"
  },
  {
   "start": 0.72,
   "end": 0.88,
   "value": "a"
  },
  {
   "start": 0.88,
   "end": 0.919,
   "value": "wr"
  },
  {
   "start": 0.919,
   "end": 0.982,
   "value": "a"
  },
  {
   "start": 0.982,
   "end": 1.021,
   "value": "ln"
  },
  {
   "start": 1.021,
   "end": 1.122,
   "value": "ts"
  },
  {
   "start": 1.122,
   "end": 1.22,
   "value": "uq"
  },
  {
   "start": 1.22,
   "end": 1.276,
   "value": "mbp"
  },
  {
   "start": 1.276,
   "end": 1.331,
   "value": "ln"
  },
  {
   "start": 1.331,
   "end": 1.42,
   "value": "e"
  },
  {
   "start": 1.42,
   "end": 1.47,
   "value": "wr"
  },
  {
   "start": 1.47,
   "end": 1.55,
   "value": "e"
  },
  {
   "start": 1.55,
   "end": 1.644,
   "value": "ts"
  },
  {
   "start": 1.644,
   "end": 1.716,
   "value": "e"
  },
  {
   "start": 1.716,
   "end": 1.891,
   "value": "ts"
  },
  {
   "start": 1.891,
   "end": 2.1,
   "value": "uq"
  },
  {
   "start": 2.1,
   "end": 2.391,
   "value": "rest"
  }
 ]
}