{
 "metadata": {
  "duration": 1.194,
  "source": "faster-whisper+cmudict"
 },
 "mouthCues": [
  {
   "start": 0.0,
   "end": 0.033,
   "value": "ts"
  },
  {
   "start": 0.033,
   "end": 0.087,
   "value": "e"
  },
  {
   "start": 0.087,
   "end": 0.12,
   "value": "ln"
  },
  {
   "start": 0.12,
   "end": 0.166,
   "value": "ts"
  },
  {
   "start": 0.166,
   "end": 0.24,
   "value": "uq"
  },
  {
   "start": 0.24,
   "end": 0.288,
   "value": "ts"
  },
  {
   "start": 0.288,
   "end": 0.364,
   "value": "e"
  },
  {
   "start": 0.364,
   "end": 0.412,
   "value": "ln"
  },
  {
   "start": 0.412,
   "end": 0.529,
   "value": "mbp"
  },
  {
   "start": 0.529,
   "end": 0.64,
   "value": "e"
  },
  {
   "start": 0.64,
   "end": 0.701,
   "value": "mbp"
  },
  {
   "start": 0.701,
   "end": 0.762,
   "value": "ln"
  },
  {
   "start": 0.762,
   "end": 0.859,
   "value": "e"
  },
  {
   "start": 0.859,
   "end": 0.92,
   "value": "ts"
  },
  {
   "start": 0.92,
   "end": 1.194,
   "value": "rest"
  }
 ]
}