{
 "metadata": {
  "duration": 2.868,
  "source": "faster-whisper+cmudict"
 },
 "mouthCues": [
  {
   "start": 0.0,
   "end": 0.18,
   "value": "o"
  },
  {
   "start": 0.18,
   "end": 0.28,
   "value": "ln"
  },
  {
   "start": 0.28,
   "end": 0.44,
   "value": "o"
  },
  {
   "start": 0.44,
   "end": 0.74,
   "value": "rest"
  },
  {
   "start": 0.74,
   "end": 0.856,
   "value": "e"
  },
  {
   "start": 0.856,
   "end": 1.062,
   "value": "ts"
  },
  {
   "start": 1.062,
   "end": 1.16,
   "value": "uq"
  },
  {
   "start": 1.16,
   "end": 1.298,
   "value": "ts"
  },
  {
   "start": 1.298,
   "end": 1.52,
   "value": "a"
  },
  {
   "start": 1.52,
   "end": 1.82,
   "value": "rest"
  },
  {
   "start": 1.82,
   "end": 1.96,
   "value": "a"
  },
  {
   "start": 1.96,
   "end": 2.025,
   "value": "ts"
  },
  {
   "start": 2.025,
   "end": 2.13,
   "value": "e"
  },
  {
   "start": 2.13,
   "end": 2.195,
   "value": "ln"
  },
  {
   "start": 2.195,
   "end": 2.26,
   "value": "ts"
  },
  {
   "start": 2.26,
   "end": 2.316,
   "value": "wr"
  },
  {
   "start": 2.316,
   "end": 2.404,
   "value": "e"
  },
  {
   "start": 2.404,
   "end": 2.46,
   "value": "ts"
  },
  {
   "start": 2.46,
   "end": 2.645,
   "value": "e"
  },
  {
   "start": 2.645,
   "end": 2.76,
   "value": "ts"
  },
  {
   "start": 2.76,
   "end": 2.868,
   "value": "rest"
  }
 ]
}